pyspin/__init__.py
pyspin/spin.py
pyspin-1.1.1.dist-info/DESCRIPTION.rst
pyspin-1.1.1.dist-info/METADATA
pyspin-1.1.1.dist-info/RECORD
pyspin-1.1.1.dist-info/WHEEL
pyspin-1.1.1.dist-info/metadata.json
pyspin-1.1.1.dist-info/top_level.txt
