Metadata-Version: 1.1
Name: pyspin
Version: 1.1.1
Summary: Little terminal spinner lib.
Home-page: http://github.com/lord63/py-spin
Author: lord63
Author-email: lord63.j@gmail.com
License: MIT
Keywords: terminal spin spinner
Platform: UNKNOWN
Classifier: Development Status :: 4 - Beta
Classifier: Intended Audience :: Developers
Classifier: Operating System :: POSIX
Classifier: Operating System :: POSIX :: Linux
Classifier: License :: OSI Approved :: MIT License
Classifier: Programming Language :: Python :: 2
Classifier: Programming Language :: Python :: 2.7
Classifier: Programming Language :: Python :: 3
Classifier: Programming Language :: Python :: 3.3
Classifier: Programming Language :: Python :: 3.4
Classifier: Programming Language :: Python :: 3.5
Classifier: Programming Language :: Python :: 3.6
